ib110hw_testing/testing/strategies.py
ib110hw_testing/transformation/transformation.py
ib110hw_testing-0.1.11.dist-info/WHEEL
ib110hw_testing-0.1.11.dist-info/METADATA
ib110hw_testing-0.1.11.dist-info/RECORD
